matchlib/__init__.py
matchlib/main.py
matchlib-0.2.3.dist-info/LICENSE
matchlib-0.2.3.dist-info/METADATA
matchlib-0.2.3.dist-info/WHEEL
matchlib-0.2.3.dist-info/top_level.txt
matchlib-0.2.3.dist-info/RECORD
