Metadata-Version: 2.1
Name: matchlib
Version: 0.2.3
Summary: A tool for partial comparison of (nested) data structures
Home-page: https://github.com/qweeze/matchlib
Author: qweeze
Author-email: qweeeze@gmail.com
License: MIT
Classifier: License :: OSI Approved :: MIT License
Classifier: Programming Language :: Python :: 3
Classifier: Programming Language :: Python :: 3.7
License-File: LICENSE
